bleemeo/__init__.py
bleemeo/_authenticator.py
bleemeo/client.py
bleemeo/enums.py
bleemeo/exceptions.py
bleemeo/py.typed
bleemeo/resources.py
bleemeo-0.8.0.dist-info/METADATA
bleemeo-0.8.0.dist-info/WHEEL
bleemeo-0.8.0.dist-info/licenses/LICENSE
bleemeo-0.8.0.dist-info/RECORD
