Metadata-Version: 2.4
Name: bleemeo
Version: 0.8.0
Summary: A simple Python3 client for interacting with the Bleemeo API.
Author-email: Bleemeo Packaging Team <packaging-team@bleemeo.com>
License-File: LICENSE
Requires-Python: >=3.8
Requires-Dist: requests
